aijobs/__init__.py
aijobs/cli/__init__.py
aijobs/cli/app.py
aijobs/cli/cmd_batch.py
aijobs/cli/cmd_online.py
aijobs/data/__init__.py
aijobs/data/common_scraper.py
aijobs/data/headers.py
aijobs/data/indeed/__init__.py
aijobs/data/indeed/selenium_scrapers.py
aijobs/data/topcv/__init__.py
aijobs/data/topcv/selenium_scrapers.py
aijobs/data/vietnamworks/__init__.py
aijobs/data/vietnamworks/selenium_scrapers.py
aijobs/mongodb/__init__.py
aijobs/utils/__init__.py
aijobs/utils/helpers.py
AIJobs_Batch-1.0.0a1.dist-info/LICENSE
AIJobs_Batch-1.0.0a1.dist-info/METADATA
AIJobs_Batch-1.0.0a1.dist-info/WHEEL
AIJobs_Batch-1.0.0a1.dist-info/entry_points.txt
AIJobs_Batch-1.0.0a1.dist-info/top_level.txt
AIJobs_Batch-1.0.0a1.dist-info/RECORD
