Metadata-Version: 2.1
Name: AIJobs-Batch
Version: 1.0.0a1
Summary: A batch to analyse AI jobs in Vietnam
Home-page: https://github.com/Ok-em-Research-Inc/okem-ai-jobs
Download-URL: https://github.com/Ok-em-Research-Inc/okem-ai-jobs/releases
Author: OK-EM Inc.
Author-email: okemdotnet@gmail.com
Maintainer: OK-EM Inc.
Maintainer-email: okemdotnet@gmail.com
License: MIT License
Keywords: ai,jobs,aijobs,vietnamworks,topcv,indeed,scrapping,jobs scrapping
Platform: win32
Platform: linux_x86_64
Platform: linux-i686
Classifier: Development Status :: 2 - Pre-Alpha
Classifier: Environment :: Web Environment
Classifier: License :: OSI Approved :: MIT License
Classifier: Operating System :: OS Independent
Classifier: Programming Language :: Python
Classifier: Programming Language :: Python :: 3
Classifier: Programming Language :: Python :: 3 :: Only
Classifier: Programming Language :: Python :: 3.7
Classifier: Programming Language :: Python :: 3.8
Classifier: Programming Language :: Python :: 3.9
Classifier: Programming Language :: Python :: 3.10
Classifier: Programming Language :: Python :: 3.11
Requires-Python: >=3.7.0
License-File: LICENSE
